ilmo_app/__init__.py
ilmo_app/admin.py
ilmo_app/config.py
ilmo_app/forms.py
ilmo_app/models.py
ilmo_app/tests.py
ilmo_app/urls.py
ilmo_app/utils.py
ilmo_app/views.py
ilmo_app-1.0.0.dist-info/DESCRIPTION.rst
ilmo_app-1.0.0.dist-info/METADATA
ilmo_app-1.0.0.dist-info/RECORD
ilmo_app-1.0.0.dist-info/WHEEL
ilmo_app-1.0.0.dist-info/metadata.json
ilmo_app-1.0.0.dist-info/top_level.txt
