Metadata-Version: 2.0
Name: ilmo-app
Version: 1.0.0
Summary: Django app for event registration
Home-page: https://github.com/osakunta/django-ilmo-app
Author: Matti Remes
Author-email: remes@iki.fi
License: MIT
Keywords: django app
Platform: UNKNOWN
Requires-Python: >=3
Requires-Dist: Babel (==2.3.4)
Requires-Dist: Django (==1.9.12)
Requires-Dist: Django-Select2 (==4.3.2)
Requires-Dist: Pillow (==4.0.0)
Requires-Dist: PyYAML (==3.11)
Requires-Dist: South (==1.0.1)
Requires-Dist: Unidecode (==0.4.20)
Requires-Dist: YURL (==0.13)
Requires-Dist: aldryn-apphooks-config (==0.3.0)
Requires-Dist: aldryn-boilerplates (==0.7.4)
Requires-Dist: aldryn-bootstrap3 (==1.1.2)
Requires-Dist: aldryn-categories (==1.0.3)
Requires-Dist: aldryn-common (==1.0.4)
Requires-Dist: aldryn-newsblog (==1.2.4)
Requires-Dist: aldryn-people (==1.2.2)
Requires-Dist: aldryn-reversion (==1.0.9)
Requires-Dist: aldryn-translation-tools (==0.2.1)
Requires-Dist: amqp (==1.4.9)
Requires-Dist: anyjson (==0.3.3)
Requires-Dist: appdirs (==1.4.0)
Requires-Dist: backport-collections (==0.1)
Requires-Dist: billiard (==3.3.0.23)
Requires-Dist: boto3 (==1.4.4)
Requires-Dist: botocore (==1.5.7)
Requires-Dist: celery (==3.1.18)
Requires-Dist: cffi (==1.9.1)
Requires-Dist: click (==6.7)
Requires-Dist: cmsplugin-filer (==1.1.3)
Requires-Dist: cmsplugin-image-gallery (==0.7.2)
Requires-Dist: contextlib2 (==0.5.4)
Requires-Dist: cryptography (==1.7.2)
Requires-Dist: cssselect (==1.0.1)
Requires-Dist: cssutils (==0.9.10)
Requires-Dist: django-appconf (==1.0.2)
Requires-Dist: django-appdata (==0.1.6)
Requires-Dist: django-bitfield (==1.7.1)
Requires-Dist: django-classy-tags (==0.8.0)
Requires-Dist: django-cms (==3.3.3)
Requires-Dist: django-crispy-forms (==1.4.0)
Requires-Dist: django-debug-toolbar (==1.3.2)
Requires-Dist: django-durationfield (==0.5.2)
Requires-Dist: django-filer (==1.2.6)
Requires-Dist: django-formtools (==2.0)
Requires-Dist: django-jsonfield (==0.9.13)
Requires-Dist: django-mptt (==0.8.7)
Requires-Dist: django-parler (==1.7)
Requires-Dist: django-phonenumber-field (==1.1.0)
Requires-Dist: django-picklefield (==0.3.2)
Requires-Dist: django-polymorphic (==1.0.2)
Requires-Dist: django-registration (==2.2)
Requires-Dist: django-reversion (==1.10.2)
Requires-Dist: django-sekizai (==0.10.0)
Requires-Dist: django-sortedm2m (==1.3.3)
Requires-Dist: django-sudo (==2.1.0)
Requires-Dist: django-taggit (==0.22.0)
Requires-Dist: django-templatetag-sugar (==1.0)
Requires-Dist: django-treebeard (==4.1.0)
Requires-Dist: djangocms-admin-style (==1.2.6.2)
Requires-Dist: djangocms-attributes-field (==0.1.2)
Requires-Dist: djangocms-column (==1.6.0)
Requires-Dist: djangocms-googlemap (==0.5.2)
Requires-Dist: djangocms-inherit (==0.2.2)
Requires-Dist: djangocms-link (==1.8.3)
Requires-Dist: djangocms-style (==1.7.0)
Requires-Dist: djangocms-text-ckeditor (==3.3.1)
Requires-Dist: djangorestframework (==2.3.14)
Requires-Dist: docutils (==0.13.1)
Requires-Dist: easy-thumbnails (==2.3)
Requires-Dist: email-reply-parser (==0.2.0)
Requires-Dist: enum34 (==1.1.6)
Requires-Dist: exam (==0.10.6)
Requires-Dist: gunicorn (==19.6.0)
Requires-Dist: hiredis (==0.1.6)
Requires-Dist: honcho (==0.7.1)
Requires-Dist: html5lib (==0.9999999)
Requires-Dist: httplib2 (==0.10.3)
Requires-Dist: idna (==2.2)
Requires-Dist: ilmo-app (==0.0.1)
Requires-Dist: ipaddress (==1.0.18)
Requires-Dist: jmespath (==0.9.1)
Requires-Dist: kombu (==3.0.35)
Requires-Dist: libsourcemap (==0.5.0)
Requires-Dist: lxml (==3.7.2)
Requires-Dist: mock (==1.0.1)
Requires-Dist: oauth2 (==1.9.0.post1)
Requires-Dist: olefile (==0.44)
Requires-Dist: packaging (==16.8)
Requires-Dist: percy (==0.4.1)
Requires-Dist: petname (==1.7)
Requires-Dist: phonenumbers (==8.2.0)
Requires-Dist: phonenumberslite (==8.2.0)
Requires-Dist: progressbar2 (==3.10.1)
Requires-Dist: psycopg2 (==2.6.2)
Requires-Dist: py (==1.4.32)
Requires-Dist: pyOpenSSL (==16.2.0)
Requires-Dist: pyasn1 (==0.2.1)
Requires-Dist: pycparser (==2.17)
Requires-Dist: pyparsing (==2.1.10)
Requires-Dist: pytest (==2.6.4)
Requires-Dist: pytest-django (==2.9.1)
Requires-Dist: pytest-html (==1.9.0)
Requires-Dist: python-dateutil (==2.6.0)
Requires-Dist: python-memcached (==1.58)
Requires-Dist: python-openid (==2.2.5)
Requires-Dist: python-slugify (==1.2.0)
Requires-Dist: python-u2flib-server (==4.0.1)
Requires-Dist: python-utils (==2.0.1)
Requires-Dist: pytz (==2016.10)
Requires-Dist: qrcode (==5.3)
Requires-Dist: raven (==5.32.0)
Requires-Dist: rb (==1.6)
Requires-Dist: redis (==2.10.5)
Requires-Dist: requests (==2.12.5)
Requires-Dist: s3transfer (==0.1.10)
Requires-Dist: selenium (==3.0.0b3)
Requires-Dist: sentry (==8.13.0)
Requires-Dist: setproctitle (==1.1.10)
Requires-Dist: simplejson (==3.8.2)
Requires-Dist: six (==1.10.0)
Requires-Dist: sqlparse (==0.2.2)
Requires-Dist: statsd (==3.1)
Requires-Dist: structlog (==16.1.0)
Requires-Dist: symsynd (==1.3.0)
Requires-Dist: toronado (==0.0.11)
Requires-Dist: uWSGI (==2.0.14)
Requires-Dist: ua-parser (==0.7.3)
Requires-Dist: urllib3 (==1.16)
Requires-Dist: webencodings (==0.5)
